{
  "fio version" : "fio-3.33",
  "timestamp" : 1747285167,
  "timestamp_ms" : 1747285167027,
  "time" : "Thu May 15 07:59:27 2025",
  "jobs" : [
    {
      "jobname" : "randwrite_B4_Q32_T4",
      "groupid" : 0,
      "error" : 0,
      "eta" : 0,
      "elapsed" : 11,
      "job options" : {
        "rw" : "randwrite",
        "name" : "randwrite_B4_Q32_T4",
        "bs" : "4k",
        "iodepth" : "32",
        "numjobs" : "4",
        "runtime" : "10",
        "direct" : "1",
        "ioengine" : "libaio",
        "size" : "1G",
        "filename" : "/mnt/pve/test/write"
      },
      "read" : {
        "io_bytes" : 0,
        "io_kbytes" : 0,
        "bw_bytes" : 0,
        "bw" : 0,
        "iops" : 0.000000,
        "runtime" : 0,
        "total_ios" : 0,
        "short_ios" : 0,
        "drop_ios" : 0,
        "slat_ns" : {
          "min" : 0,
          "max" : 0,
          "mean" : 0.000000,
          "stddev" : 0.000000,
          "N" : 0
        },
        "clat_ns" : {
          "min" : 0,
          "max" : 0,
          "mean" : 0.000000,
          "stddev" : 0.000000,
          "N" : 0
        },
        "lat_ns" : {
          "min" : 0,
          "max" : 0,
          "mean" : 0.000000,
          "stddev" : 0.000000,
          "N" : 0
        },
        "bw_min" : 0,
        "bw_max" : 0,
        "bw_agg" : 0.000000,
        "bw_mean" : 0.000000,
        "bw_dev" : 0.000000,
        "bw_samples" : 0,
        "iops_min" : 0,
        "iops_max" : 0,
        "iops_mean" : 0.000000,
        "iops_stddev" : 0.000000,
        "iops_samples" : 0
      },
      "write" : {
        "io_bytes" : 554242048,
        "io_kbytes" : 541252,
        "bw_bytes" : 55407582,
        "bw" : 54108,
        "iops" : 13527.241827,
        "runtime" : 10003,
        "total_ios" : 135313,
        "short_ios" : 0,
        "drop_ios" : 0,
        "slat_ns" : {
          "min" : 4477,
          "max" : 641727,
          "mean" : 20806.496523,
          "stddev" : 18069.444939,
          "N" : 135313
        },
        "clat_ns" : {
          "min" : 120284,
          "max" : 26059806,
          "mean" : 2341833.211643,
          "stddev" : 1306185.526356,
          "N" : 135313,
          "percentile" : {
            "1.000000" : 528384,
            "5.000000" : 684032,
            "10.000000" : 864256,
            "20.000000" : 1220608,
            "30.000000" : 1564672,
            "40.000000" : 1908736,
            "50.000000" : 2277376,
            "60.000000" : 2605056,
            "70.000000" : 2965504,
            "80.000000" : 3325952,
            "90.000000" : 3719168,
            "95.000000" : 3948544,
            "99.000000" : 6193152,
            "99.500000" : 8585216,
            "99.900000" : 14090240,
            "99.950000" : 16187392,
            "99.990000" : 20316160
          }
        },
        "lat_ns" : {
          "min" : 382979,
          "max" : 26070372,
          "mean" : 2362639.708166,
          "stddev" : 1305989.322561,
          "N" : 135313
        },
        "bw_min" : 53360,
        "bw_max" : 54896,
        "bw_agg" : 25.031091,
        "bw_mean" : 54114.526316,
        "bw_dev" : 444.494640,
        "bw_samples" : 19,
        "iops_min" : 13340,
        "iops_max" : 13724,
        "iops_mean" : 13528.631579,
        "iops_stddev" : 111.123660,
        "iops_samples" : 19
      },
      "trim" : {
        "io_bytes" : 0,
        "io_kbytes" : 0,
        "bw_bytes" : 0,
        "bw" : 0,
        "iops" : 0.000000,
        "runtime" : 0,
        "total_ios" : 0,
        "short_ios" : 0,
        "drop_ios" : 0,
        "slat_ns" : {
          "min" : 0,
          "max" : 0,
          "mean" : 0.000000,
          "stddev" : 0.000000,
          "N" : 0
        },
        "clat_ns" : {
          "min" : 0,
          "max" : 0,
          "mean" : 0.000000,
          "stddev" : 0.000000,
          "N" : 0
        },
        "lat_ns" : {
          "min" : 0,
          "max" : 0,
          "mean" : 0.000000,
          "stddev" : 0.000000,
          "N" : 0
        },
        "bw_min" : 0,
        "bw_max" : 0,
        "bw_agg" : 0.000000,
        "bw_mean" : 0.000000,
        "bw_dev" : 0.000000,
        "bw_samples" : 0,
        "iops_min" : 0,
        "iops_max" : 0,
        "iops_mean" : 0.000000,
        "iops_stddev" : 0.000000,
        "iops_samples" : 0
      },
      "sync" : {
        "total_ios" : 0,
        "lat_ns" : {
          "min" : 0,
          "max" : 0,
          "mean" : 0.000000,
          "stddev" : 0.000000,
          "N" : 0
        }
      },
      "job_runtime" : 10002,
      "usr_cpu" : 8.218356,
      "sys_cpu" : 29.704059,
      "ctx" : 86962,
      "majf" : 0,
      "minf" : 20,
      "iodepth_level" : {
        "1" : 0.100000,
        "2" : 0.100000,
        "4" : 0.100000,
        "8" : 0.100000,
        "16" : 0.100000,
        "32" : 99.977090,
        ">=64" : 0.000000
      },
      "iodepth_submit" : {
        "0" : 0.000000,
        "4" : 100.000000,
        "8" : 0.000000,
        "16" : 0.000000,
        "32" : 0.000000,
        "64" : 0.000000,
        ">=64" : 0.000000
      },
      "iodepth_complete" : {
        "0" : 0.000000,
        "4" : 99.999261,
        "8" : 0.000000,
        "16" : 0.000000,
        "32" : 0.100000,
        "64" : 0.000000,
        ">=64" : 0.000000
      },
      "latency_ns" : {
        "2" : 0.000000,
        "4" : 0.000000,
        "10" : 0.000000,
        "20" : 0.000000,
        "50" : 0.000000,
        "100" : 0.000000,
        "250" : 0.000000,
        "500" : 0.000000,
        "750" : 0.000000,
        "1000" : 0.000000
      },
      "latency_us" : {
        "2" : 0.000000,
        "4" : 0.000000,
        "10" : 0.000000,
        "20" : 0.000000,
        "50" : 0.000000,
        "100" : 0.000000,
        "250" : 0.010000,
        "500" : 0.403509,
        "750" : 6.452447,
        "1000" : 7.127918
      },
      "latency_ms" : {
        "2" : 28.386777,
        "4" : 53.412459,
        "10" : 3.882110,
        "20" : 0.321477,
        "50" : 0.011085,
        "100" : 0.000000,
        "250" : 0.000000,
        "500" : 0.000000,
        "750" : 0.000000,
        "1000" : 0.000000,
        "2000" : 0.000000,
        ">=2000" : 0.000000
      },
      "latency_depth" : 32,
      "latency_target" : 0,
      "latency_percentile" : 100.000000,
      "latency_window" : 0
    },
    {
      "jobname" : "test",
      "groupid" : 0,
      "error" : 0,
      "eta" : 0,
      "elapsed" : 11,
      "job options" : {
        "rw" : "randwrite",
        "name" : "randwrite_B4_Q32_T4",
        "bs" : "4k",
        "iodepth" : "32",
        "numjobs" : "4",
        "runtime" : "10",
        "direct" : "1",
        "ioengine" : "libaio",
        "size" : "1G",
        "filename" : "/mnt/pve/test/write"
      },
      "read" : {
        "io_bytes" : 0,
        "io_kbytes" : 0,
        "bw_bytes" : 0,
        "bw" : 0,
        "iops" : 0.000000,
        "runtime" : 0,
        "total_ios" : 0,
        "short_ios" : 0,
        "drop_ios" : 0,
        "slat_ns" : {
          "min" : 0,
          "max" : 0,
          "mean" : 0.000000,
          "stddev" : 0.000000,
          "N" : 0
        },
        "clat_ns" : {
          "min" : 0,
          "max" : 0,
          "mean" : 0.000000,
          "stddev" : 0.000000,
          "N" : 0
        },
        "lat_ns" : {
          "min" : 0,
          "max" : 0,
          "mean" : 0.000000,
          "stddev" : 0.000000,
          "N" : 0
        },
        "bw_min" : 0,
        "bw_max" : 0,
        "bw_agg" : 0.000000,
        "bw_mean" : 0.000000,
        "bw_dev" : 0.000000,
        "bw_samples" : 0,
        "iops_min" : 0,
        "iops_max" : 0,
        "iops_mean" : 0.000000,
        "iops_stddev" : 0.000000,
        "iops_samples" : 0
      },
      "write" : {
        "io_bytes" : 551821312,
        "io_kbytes" : 538888,
        "bw_bytes" : 55165581,
        "bw" : 53872,
        "iops" : 13468.159552,
        "runtime" : 10003,
        "total_ios" : 134722,
        "short_ios" : 0,
        "drop_ios" : 0,
        "slat_ns" : {
          "min" : 6708,
          "max" : 665465,
          "mean" : 20614.501232,
          "stddev" : 17948.674725,
          "N" : 134722
        },
        "clat_ns" : {
          "min" : 336598,
          "max" : 24560078,
          "mean" : 2352364.972217,
          "stddev" : 1311910.095448,
          "N" : 134722,
          "percentile" : {
            "1.000000" : 528384,
            "5.000000" : 684032,
            "10.000000" : 864256,
            "20.000000" : 1220608,
            "30.000000" : 1564672,
            "40.000000" : 1925120,
            "50.000000" : 2277376,
            "60.000000" : 2637824,
            "70.000000" : 2998272,
            "80.000000" : 3325952,
            "90.000000" : 3719168,
            "95.000000" : 3948544,
            "99.000000" : 6389760,
            "99.500000" : 8847360,
            "99.900000" : 13697024,
            "99.950000" : 15925248,
            "99.990000" : 20840448
          }
        },
        "lat_ns" : {
          "min" : 432903,
          "max" : 24570583,
          "mean" : 2372979.473449,
          "stddev" : 1311838.330166,
          "N" : 134722
        },
        "bw_min" : 53344,
        "bw_max" : 54424,
        "bw_agg" : 24.949680,
        "bw_mean" : 53938.947368,
        "bw_dev" : 280.953431,
        "bw_samples" : 19,
        "iops_min" : 13336,
        "iops_max" : 13606,
        "iops_mean" : 13484.736842,
        "iops_stddev" : 70.238358,
        "iops_samples" : 19
      },
      "trim" : {
        "io_bytes" : 0,
        "io_kbytes" : 0,
        "bw_bytes" : 0,
        "bw" : 0,
        "iops" : 0.000000,
        "runtime" : 0,
        "total_ios" : 0,
        "short_ios" : 0,
        "drop_ios" : 0,
        "slat_ns" : {
          "min" : 0,
          "max" : 0,
          "mean" : 0.000000,
          "stddev" : 0.000000,
          "N" : 0
        },
        "clat_ns" : {
          "min" : 0,
          "max" : 0,
          "mean" : 0.000000,
          "stddev" : 0.000000,
          "N" : 0
        },
        "lat_ns" : {
          "min" : 0,
          "max" : 0,
          "mean" : 0.000000,
          "stddev" : 0.000000,
          "N" : 0
        },
        "bw_min" : 0,
        "bw_max" : 0,
        "bw_agg" : 0.000000,
        "bw_mean" : 0.000000,
        "bw_dev" : 0.000000,
        "bw_samples" : 0,
        "iops_min" : 0,
        "iops_max" : 0,
        "iops_mean" : 0.000000,
        "iops_stddev" : 0.000000,
        "iops_samples" : 0
      },
      "sync" : {
        "total_ios" : 0,
        "lat_ns" : {
          "min" : 0,
          "max" : 0,
          "mean" : 0.000000,
          "stddev" : 0.000000,
          "N" : 0
        }
      },
      "job_runtime" : 10002,
      "usr_cpu" : 9.088182,
      "sys_cpu" : 28.504299,
      "ctx" : 86778,
      "majf" : 0,
      "minf" : 110,
      "iodepth_level" : {
        "1" : 0.100000,
        "2" : 0.100000,
        "4" : 0.100000,
        "8" : 0.100000,
        "16" : 0.100000,
        "32" : 99.976990,
        ">=64" : 0.000000
      },
      "iodepth_submit" : {
        "0" : 0.000000,
        "4" : 100.000000,
        "8" : 0.000000,
        "16" : 0.000000,
        "32" : 0.000000,
        "64" : 0.000000,
        ">=64" : 0.000000
      },
      "iodepth_complete" : {
        "0" : 0.000000,
        "4" : 99.999258,
        "8" : 0.000000,
        "16" : 0.000000,
        "32" : 0.100000,
        "64" : 0.000000,
        ">=64" : 0.000000
      },
      "latency_ns" : {
        "2" : 0.000000,
        "4" : 0.000000,
        "10" : 0.000000,
        "20" : 0.000000,
        "50" : 0.000000,
        "100" : 0.000000,
        "250" : 0.000000,
        "500" : 0.000000,
        "750" : 0.000000,
        "1000" : 0.000000
      },
      "latency_us" : {
        "2" : 0.000000,
        "4" : 0.000000,
        "10" : 0.000000,
        "20" : 0.000000,
        "50" : 0.000000,
        "100" : 0.000000,
        "250" : 0.000000,
        "500" : 0.414186,
        "750" : 6.480753,
        "1000" : 6.969908
      },
      "latency_ms" : {
        "2" : 28.155016,
        "4" : 53.618563,
        "10" : 4.026068,
        "20" : 0.321403,
        "50" : 0.014103,
        "100" : 0.000000,
        "250" : 0.000000,
        "500" : 0.000000,
        "750" : 0.000000,
        "1000" : 0.000000,
        "2000" : 0.000000,
        ">=2000" : 0.000000
      },
      "latency_depth" : 32,
      "latency_target" : 0,
      "latency_percentile" : 100.000000,
      "latency_window" : 0
    },
    {
      "jobname" : "test",
      "groupid" : 0,
      "error" : 0,
      "eta" : 0,
      "elapsed" : 11,
      "job options" : {
        "rw" : "randwrite",
        "name" : "randwrite_B4_Q32_T4",
        "bs" : "4k",
        "iodepth" : "32",
        "numjobs" : "4",
        "runtime" : "10",
        "direct" : "1",
        "ioengine" : "libaio",
        "size" : "1G",
        "filename" : "/mnt/pve/test/write"
      },
      "read" : {
        "io_bytes" : 0,
        "io_kbytes" : 0,
        "bw_bytes" : 0,
        "bw" : 0,
        "iops" : 0.000000,
        "runtime" : 0,
        "total_ios" : 0,
        "short_ios" : 0,
        "drop_ios" : 0,
        "slat_ns" : {
          "min" : 0,
          "max" : 0,
          "mean" : 0.000000,
          "stddev" : 0.000000,
          "N" : 0
        },
        "clat_ns" : {
          "min" : 0,
          "max" : 0,
          "mean" : 0.000000,
          "stddev" : 0.000000,
          "N" : 0
        },
        "lat_ns" : {
          "min" : 0,
          "max" : 0,
          "mean" : 0.000000,
          "stddev" : 0.000000,
          "N" : 0
        },
        "bw_min" : 0,
        "bw_max" : 0,
        "bw_agg" : 0.000000,
        "bw_mean" : 0.000000,
        "bw_dev" : 0.000000,
        "bw_samples" : 0,
        "iops_min" : 0,
        "iops_max" : 0,
        "iops_mean" : 0.000000,
        "iops_stddev" : 0.000000,
        "iops_samples" : 0
      },
      "write" : {
        "io_bytes" : 554905600,
        "io_kbytes" : 541900,
        "bw_bytes" : 55473917,
        "bw" : 54173,
        "iops" : 13543.436969,
        "runtime" : 10003,
        "total_ios" : 135475,
        "short_ios" : 0,
        "drop_ios" : 0,
        "slat_ns" : {
          "min" : 4901,
          "max" : 718316,
          "mean" : 20809.807573,
          "stddev" : 18000.476925,
          "N" : 135475
        },
        "clat_ns" : {
          "min" : 364187,
          "max" : 24193217,
          "mean" : 2338936.515852,
          "stddev" : 1295588.801830,
          "N" : 135475,
          "percentile" : {
            "1.000000" : 528384,
            "5.000000" : 675840,
            "10.000000" : 856064,
            "20.000000" : 1204224,
            "30.000000" : 1564672,
            "40.000000" : 1908736,
            "50.000000" : 2277376,
            "60.000000" : 2605056,
            "70.000000" : 2965504,
            "80.000000" : 3325952,
            "90.000000" : 3719168,
            "95.000000" : 3948544,
            "99.000000" : 6193152,
            "99.500000" : 8585216,
            "99.900000" : 13303808,
            "99.950000" : 15925248,
            "99.990000" : 19791872
          }
        },
        "lat_ns" : {
          "min" : 406997,
          "max" : 24210311,
          "mean" : 2359746.323425,
          "stddev" : 1295538.478549,
          "N" : 135475
        },
        "bw_min" : 53128,
        "bw_max" : 55072,
        "bw_agg" : 25.076884,
        "bw_mean" : 54213.473684,
        "bw_dev" : 517.024324,
        "bw_samples" : 19,
        "iops_min" : 13282,
        "iops_max" : 13768,
        "iops_mean" : 13553.368421,
        "iops_stddev" : 129.256081,
        "iops_samples" : 19
      },
      "trim" : {
        "io_bytes" : 0,
        "io_kbytes" : 0,
        "bw_bytes" : 0,
        "bw" : 0,
        "iops" : 0.000000,
        "runtime" : 0,
        "total_ios" : 0,
        "short_ios" : 0,
        "drop_ios" : 0,
        "slat_ns" : {
          "min" : 0,
          "max" : 0,
          "mean" : 0.000000,
          "stddev" : 0.000000,
          "N" : 0
        },
        "clat_ns" : {
          "min" : 0,
          "max" : 0,
          "mean" : 0.000000,
          "stddev" : 0.000000,
          "N" : 0
        },
        "lat_ns" : {
          "min" : 0,
          "max" : 0,
          "mean" : 0.000000,
          "stddev" : 0.000000,
          "N" : 0
        },
        "bw_min" : 0,
        "bw_max" : 0,
        "bw_agg" : 0.000000,
        "bw_mean" : 0.000000,
        "bw_dev" : 0.000000,
        "bw_samples" : 0,
        "iops_min" : 0,
        "iops_max" : 0,
        "iops_mean" : 0.000000,
        "iops_stddev" : 0.000000,
        "iops_samples" : 0
      },
      "sync" : {
        "total_ios" : 0,
        "lat_ns" : {
          "min" : 0,
          "max" : 0,
          "mean" : 0.000000,
          "stddev" : 0.000000,
          "N" : 0
        }
      },
      "job_runtime" : 10002,
      "usr_cpu" : 8.598280,
      "sys_cpu" : 29.394121,
      "ctx" : 87029,
      "majf" : 0,
      "minf" : 15,
      "iodepth_level" : {
        "1" : 0.100000,
        "2" : 0.100000,
        "4" : 0.100000,
        "8" : 0.100000,
        "16" : 0.100000,
        "32" : 99.977118,
        ">=64" : 0.000000
      },
      "iodepth_submit" : {
        "0" : 0.000000,
        "4" : 100.000000,
        "8" : 0.000000,
        "16" : 0.000000,
        "32" : 0.000000,
        "64" : 0.000000,
        ">=64" : 0.000000
      },
      "iodepth_complete" : {
        "0" : 0.000000,
        "4" : 99.999262,
        "8" : 0.000000,
        "16" : 0.000000,
        "32" : 0.100000,
        "64" : 0.000000,
        ">=64" : 0.000000
      },
      "latency_ns" : {
        "2" : 0.000000,
        "4" : 0.000000,
        "10" : 0.000000,
        "20" : 0.000000,
        "50" : 0.000000,
        "100" : 0.000000,
        "250" : 0.000000,
        "500" : 0.000000,
        "750" : 0.000000,
        "1000" : 0.000000
      },
      "latency_us" : {
        "2" : 0.000000,
        "4" : 0.000000,
        "10" : 0.000000,
        "20" : 0.000000,
        "50" : 0.000000,
        "100" : 0.000000,
        "250" : 0.000000,
        "500" : 0.409670,
        "750" : 6.467614,
        "1000" : 7.162945
      },
      "latency_ms" : {
        "2" : 28.492342,
        "4" : 53.233438,
        "10" : 3.915852,
        "20" : 0.308544,
        "50" : 0.010000,
        "100" : 0.000000,
        "250" : 0.000000,
        "500" : 0.000000,
        "750" : 0.000000,
        "1000" : 0.000000,
        "2000" : 0.000000,
        ">=2000" : 0.000000
      },
      "latency_depth" : 32,
      "latency_target" : 0,
      "latency_percentile" : 100.000000,
      "latency_window" : 0
    },
    {
      "jobname" : "test",
      "groupid" : 0,
      "error" : 0,
      "eta" : 0,
      "elapsed" : 11,
      "job options" : {
        "rw" : "randwrite",
        "name" : "randwrite_B4_Q32_T4",
        "bs" : "4k",
        "iodepth" : "32",
        "numjobs" : "4",
        "runtime" : "10",
        "direct" : "1",
        "ioengine" : "libaio",
        "size" : "1G",
        "filename" : "/mnt/pve/test/write"
      },
      "read" : {
        "io_bytes" : 0,
        "io_kbytes" : 0,
        "bw_bytes" : 0,
        "bw" : 0,
        "iops" : 0.000000,
        "runtime" : 0,
        "total_ios" : 0,
        "short_ios" : 0,
        "drop_ios" : 0,
        "slat_ns" : {
          "min" : 0,
          "max" : 0,
          "mean" : 0.000000,
          "stddev" : 0.000000,
          "N" : 0
        },
        "clat_ns" : {
          "min" : 0,
          "max" : 0,
          "mean" : 0.000000,
          "stddev" : 0.000000,
          "N" : 0
        },
        "lat_ns" : {
          "min" : 0,
          "max" : 0,
          "mean" : 0.000000,
          "stddev" : 0.000000,
          "N" : 0
        },
        "bw_min" : 0,
        "bw_max" : 0,
        "bw_agg" : 0.000000,
        "bw_mean" : 0.000000,
        "bw_dev" : 0.000000,
        "bw_samples" : 0,
        "iops_min" : 0,
        "iops_max" : 0,
        "iops_mean" : 0.000000,
        "iops_stddev" : 0.000000,
        "iops_samples" : 0
      },
      "write" : {
        "io_bytes" : 553451520,
        "io_kbytes" : 540480,
        "bw_bytes" : 55328553,
        "bw" : 54031,
        "iops" : 13507.947616,
        "runtime" : 10003,
        "total_ios" : 135120,
        "short_ios" : 0,
        "drop_ios" : 0,
        "slat_ns" : {
          "min" : 4782,
          "max" : 997080,
          "mean" : 20640.669242,
          "stddev" : 18031.994120,
          "N" : 135120
        },
        "clat_ns" : {
          "min" : 296452,
          "max" : 24821135,
          "mean" : 2345328.074201,
          "stddev" : 1312454.066289,
          "N" : 135120,
          "percentile" : {
            "1.000000" : 528384,
            "5.000000" : 684032,
            "10.000000" : 856064,
            "20.000000" : 1220608,
            "30.000000" : 1564672,
            "40.000000" : 1908736,
            "50.000000" : 2277376,
            "60.000000" : 2637824,
            "70.000000" : 2965504,
            "80.000000" : 3325952,
            "90.000000" : 3719168,
            "95.000000" : 3948544,
            "99.000000" : 6520832,
            "99.500000" : 8847360,
            "99.900000" : 14090240,
            "99.950000" : 15532032,
            "99.990000" : 19529728
          }
        },
        "lat_ns" : {
          "min" : 368562,
          "max" : 24831444,
          "mean" : 2365968.743443,
          "stddev" : 1312439.049363,
          "N" : 135120
        },
        "bw_min" : 53512,
        "bw_max" : 54720,
        "bw_agg" : 24.999174,
        "bw_mean" : 54045.894737,
        "bw_dev" : 387.308360,
        "bw_samples" : 19,
        "iops_min" : 13378,
        "iops_max" : 13680,
        "iops_mean" : 13511.473684,
        "iops_stddev" : 96.827090,
        "iops_samples" : 19
      },
      "trim" : {
        "io_bytes" : 0,
        "io_kbytes" : 0,
        "bw_bytes" : 0,
        "bw" : 0,
        "iops" : 0.000000,
        "runtime" : 0,
        "total_ios" : 0,
        "short_ios" : 0,
        "drop_ios" : 0,
        "slat_ns" : {
          "min" : 0,
          "max" : 0,
          "mean" : 0.000000,
          "stddev" : 0.000000,
          "N" : 0
        },
        "clat_ns" : {
          "min" : 0,
          "max" : 0,
          "mean" : 0.000000,
          "stddev" : 0.000000,
          "N" : 0
        },
        "lat_ns" : {
          "min" : 0,
          "max" : 0,
          "mean" : 0.000000,
          "stddev" : 0.000000,
          "N" : 0
        },
        "bw_min" : 0,
        "bw_max" : 0,
        "bw_agg" : 0.000000,
        "bw_mean" : 0.000000,
        "bw_dev" : 0.000000,
        "bw_samples" : 0,
        "iops_min" : 0,
        "iops_max" : 0,
        "iops_mean" : 0.000000,
        "iops_stddev" : 0.000000,
        "iops_samples" : 0
      },
      "sync" : {
        "total_ios" : 0,
        "lat_ns" : {
          "min" : 0,
          "max" : 0,
          "mean" : 0.000000,
          "stddev" : 0.000000,
          "N" : 0
        }
      },
      "job_runtime" : 10002,
      "usr_cpu" : 8.818236,
      "sys_cpu" : 28.824235,
      "ctx" : 87179,
      "majf" : 0,
      "minf" : 95,
      "iodepth_level" : {
        "1" : 0.100000,
        "2" : 0.100000,
        "4" : 0.100000,
        "8" : 0.100000,
        "16" : 0.100000,
        "32" : 99.977057,
        ">=64" : 0.000000
      },
      "iodepth_submit" : {
        "0" : 0.000000,
        "4" : 100.000000,
        "8" : 0.000000,
        "16" : 0.000000,
        "32" : 0.000000,
        "64" : 0.000000,
        ">=64" : 0.000000
      },
      "iodepth_complete" : {
        "0" : 0.000000,
        "4" : 99.999260,
        "8" : 0.000000,
        "16" : 0.000000,
        "32" : 0.100000,
        "64" : 0.000000,
        ">=64" : 0.000000
      },
      "latency_ns" : {
        "2" : 0.000000,
        "4" : 0.000000,
        "10" : 0.000000,
        "20" : 0.000000,
        "50" : 0.000000,
        "100" : 0.000000,
        "250" : 0.000000,
        "500" : 0.000000,
        "750" : 0.000000,
        "1000" : 0.000000
      },
      "latency_us" : {
        "2" : 0.000000,
        "4" : 0.000000,
        "10" : 0.000000,
        "20" : 0.000000,
        "50" : 0.000000,
        "100" : 0.000000,
        "250" : 0.000000,
        "500" : 0.377442,
        "750" : 6.492007,
        "1000" : 7.195086
      },
      "latency_ms" : {
        "2" : 28.304470,
        "4" : 53.264506,
        "10" : 4.027531,
        "20" : 0.333037,
        "50" : 0.010000,
        "100" : 0.000000,
        "250" : 0.000000,
        "500" : 0.000000,
        "750" : 0.000000,
        "1000" : 0.000000,
        "2000" : 0.000000,
        ">=2000" : 0.000000
      },
      "latency_depth" : 32,
      "latency_target" : 0,
      "latency_percentile" : 100.000000,
      "latency_window" : 0
    }
  ],
  "disk_util" : [
    {
      "name" : "sdb",
      "read_ios" : 0,
      "write_ios" : 534000,
      "read_merges" : 0,
      "write_merges" : 460,
      "read_ticks" : 0,
      "write_ticks" : 1227513,
      "in_queue" : 1227513,
      "util" : 99.018823
    }
  ]
}
