{
  "fio version" : "fio-3.33",
  "timestamp" : 1747293719,
  "timestamp_ms" : 1747293719001,
  "time" : "Thu May 15 10:21:59 2025",
  "jobs" : [
    {
      "jobname" : "read_B4096_Q32_T1",
      "groupid" : 0,
      "error" : 0,
      "eta" : 0,
      "elapsed" : 3,
      "job options" : {
        "rw" : "read",
        "name" : "read_B4096_Q32_T1",
        "bs" : "4096k",
        "iodepth" : "32",
        "numjobs" : "1",
        "runtime" : "10",
        "direct" : "1",
        "ioengine" : "libaio",
        "size" : "1G",
        "filename" : "/mnt/pve/test/write"
      },
      "read" : {
        "io_bytes" : 1073741824,
        "io_kbytes" : 1048576,
        "bw_bytes" : 510819136,
        "bw" : 498846,
        "iops" : 121.788773,
        "runtime" : 2102,
        "total_ios" : 256,
        "short_ios" : 0,
        "drop_ios" : 0,
        "slat_ns" : {
          "min" : 3837064,
          "max" : 12228096,
          "mean" : 7939913.949219,
          "stddev" : 1202350.402933,
          "N" : 256
        },
        "clat_ns" : {
          "min" : 65902185,
          "max" : 309517837,
          "mean" : 244311581.738281,
          "stddev" : 33658959.859986,
          "N" : 256,
          "percentile" : {
            "1.000000" : 83361792,
            "5.000000" : 166723584,
            "10.000000" : 221249536,
            "20.000000" : 250609664,
            "30.000000" : 250609664,
            "40.000000" : 252706816,
            "50.000000" : 252706816,
            "60.000000" : 254803968,
            "70.000000" : 254803968,
            "80.000000" : 254803968,
            "90.000000" : 258998272,
            "95.000000" : 258998272,
            "99.000000" : 295698432,
            "99.500000" : 299892736,
            "99.900000" : 308281344,
            "99.950000" : 308281344,
            "99.990000" : 308281344
          }
        },
        "lat_ns" : {
          "min" : 74287907,
          "max" : 319645085,
          "mean" : 252251495.687500,
          "stddev" : 33805679.471025,
          "N" : 256
        },
        "bw_min" : 302499,
        "bw_max" : 507904,
        "bw_agg" : 90.700389,
        "bw_mean" : 452456.750000,
        "bw_dev" : 100269.735133,
        "bw_samples" : 4,
        "iops_min" : 73,
        "iops_max" : 124,
        "iops_mean" : 110.250000,
        "iops_stddev" : 24.904819,
        "iops_samples" : 4
      },
      "write" : {
        "io_bytes" : 0,
        "io_kbytes" : 0,
        "bw_bytes" : 0,
        "bw" : 0,
        "iops" : 0.000000,
        "runtime" : 0,
        "total_ios" : 0,
        "short_ios" : 0,
        "drop_ios" : 0,
        "slat_ns" : {
          "min" : 0,
          "max" : 0,
          "mean" : 0.000000,
          "stddev" : 0.000000,
          "N" : 0
        },
        "clat_ns" : {
          "min" : 0,
          "max" : 0,
          "mean" : 0.000000,
          "stddev" : 0.000000,
          "N" : 0
        },
        "lat_ns" : {
          "min" : 0,
          "max" : 0,
          "mean" : 0.000000,
          "stddev" : 0.000000,
          "N" : 0
        },
        "bw_min" : 0,
        "bw_max" : 0,
        "bw_agg" : 0.000000,
        "bw_mean" : 0.000000,
        "bw_dev" : 0.000000,
        "bw_samples" : 0,
        "iops_min" : 0,
        "iops_max" : 0,
        "iops_mean" : 0.000000,
        "iops_stddev" : 0.000000,
        "iops_samples" : 0
      },
      "trim" : {
        "io_bytes" : 0,
        "io_kbytes" : 0,
        "bw_bytes" : 0,
        "bw" : 0,
        "iops" : 0.000000,
        "runtime" : 0,
        "total_ios" : 0,
        "short_ios" : 0,
        "drop_ios" : 0,
        "slat_ns" : {
          "min" : 0,
          "max" : 0,
          "mean" : 0.000000,
          "stddev" : 0.000000,
          "N" : 0
        },
        "clat_ns" : {
          "min" : 0,
          "max" : 0,
          "mean" : 0.000000,
          "stddev" : 0.000000,
          "N" : 0
        },
        "lat_ns" : {
          "min" : 0,
          "max" : 0,
          "mean" : 0.000000,
          "stddev" : 0.000000,
          "N" : 0
        },
        "bw_min" : 0,
        "bw_max" : 0,
        "bw_agg" : 0.000000,
        "bw_mean" : 0.000000,
        "bw_dev" : 0.000000,
        "bw_samples" : 0,
        "iops_min" : 0,
        "iops_max" : 0,
        "iops_mean" : 0.000000,
        "iops_stddev" : 0.000000,
        "iops_samples" : 0
      },
      "sync" : {
        "total_ios" : 0,
        "lat_ns" : {
          "min" : 0,
          "max" : 0,
          "mean" : 0.000000,
          "stddev" : 0.000000,
          "N" : 0
        }
      },
      "job_runtime" : 2101,
      "usr_cpu" : 0.095193,
      "sys_cpu" : 10.518801,
      "ctx" : 1181,
      "majf" : 0,
      "minf" : 32778,
      "iodepth_level" : {
        "1" : 0.390625,
        "2" : 0.781250,
        "4" : 1.562500,
        "8" : 3.125000,
        "16" : 6.250000,
        "32" : 87.890625,
        ">=64" : 0.000000
      },
      "iodepth_submit" : {
        "0" : 0.000000,
        "4" : 100.000000,
        "8" : 0.000000,
        "16" : 0.000000,
        "32" : 0.000000,
        "64" : 0.000000,
        ">=64" : 0.000000
      },
      "iodepth_complete" : {
        "0" : 0.000000,
        "4" : 99.557522,
        "8" : 0.000000,
        "16" : 0.000000,
        "32" : 0.442478,
        "64" : 0.000000,
        ">=64" : 0.000000
      },
      "latency_ns" : {
        "2" : 0.000000,
        "4" : 0.000000,
        "10" : 0.000000,
        "20" : 0.000000,
        "50" : 0.000000,
        "100" : 0.000000,
        "250" : 0.000000,
        "500" : 0.000000,
        "750" : 0.000000,
        "1000" : 0.000000
      },
      "latency_us" : {
        "2" : 0.000000,
        "4" : 0.000000,
        "10" : 0.000000,
        "20" : 0.000000,
        "50" : 0.000000,
        "100" : 0.000000,
        "250" : 0.000000,
        "500" : 0.000000,
        "750" : 0.000000,
        "1000" : 0.000000
      },
      "latency_ms" : {
        "2" : 0.000000,
        "4" : 0.000000,
        "10" : 0.000000,
        "20" : 0.000000,
        "50" : 0.000000,
        "100" : 1.953125,
        "250" : 16.796875,
        "500" : 81.250000,
        "750" : 0.000000,
        "1000" : 0.000000,
        "2000" : 0.000000,
        ">=2000" : 0.000000
      },
      "latency_depth" : 32,
      "latency_target" : 0,
      "latency_percentile" : 100.000000,
      "latency_window" : 0
    }
  ],
  "disk_util" : [
    {
      "name" : "sdb",
      "read_ios" : 7491,
      "write_ios" : 82,
      "read_merges" : 0,
      "write_merges" : 2,
      "read_ticks" : 461122,
      "write_ticks" : 1109,
      "in_queue" : 462230,
      "util" : 94.989980
    }
  ]
}
