{
  "fio version" : "fio-3.33",
  "timestamp" : 1747290039,
  "timestamp_ms" : 1747290039060,
  "time" : "Thu May 15 09:20:39 2025",
  "jobs" : [
    {
      "jobname" : "read_B4096_Q1_T4",
      "groupid" : 0,
      "error" : 0,
      "eta" : 0,
      "elapsed" : 11,
      "job options" : {
        "rw" : "read",
        "name" : "read_B4096_Q1_T4",
        "bs" : "4096k",
        "iodepth" : "1",
        "numjobs" : "4",
        "runtime" : "10",
        "direct" : "1",
        "ioengine" : "libaio",
        "size" : "1G",
        "filename" : "/mnt/pve/test/write"
      },
      "read" : {
        "io_bytes" : 767557632,
        "io_kbytes" : 749568,
        "bw_bytes" : 76725073,
        "bw" : 74926,
        "iops" : 18.292683,
        "runtime" : 10004,
        "total_ios" : 183,
        "short_ios" : 0,
        "drop_ios" : 0,
        "slat_ns" : {
          "min" : 28580493,
          "max" : 94598695,
          "mean" : 47588001.174863,
          "stddev" : 7737419.741763,
          "N" : 183
        },
        "clat_ns" : {
          "min" : 889383,
          "max" : 32910201,
          "mean" : 7068531.163934,
          "stddev" : 4558799.122650,
          "N" : 183,
          "percentile" : {
            "1.000000" : 1073152,
            "5.000000" : 1892352,
            "10.000000" : 2375680,
            "20.000000" : 3522560,
            "30.000000" : 4046848,
            "40.000000" : 5079040,
            "50.000000" : 5996544,
            "60.000000" : 7438336,
            "70.000000" : 8716288,
            "80.000000" : 10027008,
            "90.000000" : 12779520,
            "95.000000" : 14876672,
            "99.000000" : 28180480,
            "99.500000" : 32899072,
            "99.900000" : 32899072,
            "99.950000" : 32899072,
            "99.990000" : 32899072
          }
        },
        "lat_ns" : {
          "min" : 32622657,
          "max" : 109138716,
          "mean" : 54656532.338798,
          "stddev" : 9414831.862763,
          "N" : 183
        },
        "bw_min" : 49152,
        "bw_max" : 81920,
        "bw_agg" : 25.113363,
        "bw_mean" : 74590.315789,
        "bw_dev" : 8143.952665,
        "bw_samples" : 19,
        "iops_min" : 12,
        "iops_max" : 20,
        "iops_mean" : 18.210526,
        "iops_stddev" : 1.988270,
        "iops_samples" : 19
      },
      "write" : {
        "io_bytes" : 0,
        "io_kbytes" : 0,
        "bw_bytes" : 0,
        "bw" : 0,
        "iops" : 0.000000,
        "runtime" : 0,
        "total_ios" : 0,
        "short_ios" : 0,
        "drop_ios" : 0,
        "slat_ns" : {
          "min" : 0,
          "max" : 0,
          "mean" : 0.000000,
          "stddev" : 0.000000,
          "N" : 0
        },
        "clat_ns" : {
          "min" : 0,
          "max" : 0,
          "mean" : 0.000000,
          "stddev" : 0.000000,
          "N" : 0
        },
        "lat_ns" : {
          "min" : 0,
          "max" : 0,
          "mean" : 0.000000,
          "stddev" : 0.000000,
          "N" : 0
        },
        "bw_min" : 0,
        "bw_max" : 0,
        "bw_agg" : 0.000000,
        "bw_mean" : 0.000000,
        "bw_dev" : 0.000000,
        "bw_samples" : 0,
        "iops_min" : 0,
        "iops_max" : 0,
        "iops_mean" : 0.000000,
        "iops_stddev" : 0.000000,
        "iops_samples" : 0
      },
      "trim" : {
        "io_bytes" : 0,
        "io_kbytes" : 0,
        "bw_bytes" : 0,
        "bw" : 0,
        "iops" : 0.000000,
        "runtime" : 0,
        "total_ios" : 0,
        "short_ios" : 0,
        "drop_ios" : 0,
        "slat_ns" : {
          "min" : 0,
          "max" : 0,
          "mean" : 0.000000,
          "stddev" : 0.000000,
          "N" : 0
        },
        "clat_ns" : {
          "min" : 0,
          "max" : 0,
          "mean" : 0.000000,
          "stddev" : 0.000000,
          "N" : 0
        },
        "lat_ns" : {
          "min" : 0,
          "max" : 0,
          "mean" : 0.000000,
          "stddev" : 0.000000,
          "N" : 0
        },
        "bw_min" : 0,
        "bw_max" : 0,
        "bw_agg" : 0.000000,
        "bw_mean" : 0.000000,
        "bw_dev" : 0.000000,
        "bw_samples" : 0,
        "iops_min" : 0,
        "iops_max" : 0,
        "iops_mean" : 0.000000,
        "iops_stddev" : 0.000000,
        "iops_samples" : 0
      },
      "sync" : {
        "total_ios" : 0,
        "lat_ns" : {
          "min" : 0,
          "max" : 0,
          "mean" : 0.000000,
          "stddev" : 0.000000,
          "N" : 0
        }
      },
      "job_runtime" : 10003,
      "usr_cpu" : 0.019994,
      "sys_cpu" : 10.316905,
      "ctx" : 39661,
      "majf" : 0,
      "minf" : 2153,
      "iodepth_level" : {
        "1" : 100.000000,
        "2" : 0.000000,
        "4" : 0.000000,
        "8" : 0.000000,
        "16" : 0.000000,
        "32" : 0.000000,
        ">=64" : 0.000000
      },
      "iodepth_submit" : {
        "0" : 0.000000,
        "4" : 100.000000,
        "8" : 0.000000,
        "16" : 0.000000,
        "32" : 0.000000,
        "64" : 0.000000,
        ">=64" : 0.000000
      },
      "iodepth_complete" : {
        "0" : 0.000000,
        "4" : 100.000000,
        "8" : 0.000000,
        "16" : 0.000000,
        "32" : 0.000000,
        "64" : 0.000000,
        ">=64" : 0.000000
      },
      "latency_ns" : {
        "2" : 0.000000,
        "4" : 0.000000,
        "10" : 0.000000,
        "20" : 0.000000,
        "50" : 0.000000,
        "100" : 0.000000,
        "250" : 0.000000,
        "500" : 0.000000,
        "750" : 0.000000,
        "1000" : 0.000000
      },
      "latency_us" : {
        "2" : 0.000000,
        "4" : 0.000000,
        "10" : 0.000000,
        "20" : 0.000000,
        "50" : 0.000000,
        "100" : 0.000000,
        "250" : 0.000000,
        "500" : 0.000000,
        "750" : 0.000000,
        "1000" : 0.546448
      },
      "latency_ms" : {
        "2" : 4.918033,
        "4" : 22.950820,
        "10" : 51.366120,
        "20" : 18.579235,
        "50" : 1.639344,
        "100" : 0.000000,
        "250" : 0.000000,
        "500" : 0.000000,
        "750" : 0.000000,
        "1000" : 0.000000,
        "2000" : 0.000000,
        ">=2000" : 0.000000
      },
      "latency_depth" : 1,
      "latency_target" : 0,
      "latency_percentile" : 100.000000,
      "latency_window" : 0
    },
    {
      "jobname" : "test",
      "groupid" : 0,
      "error" : 0,
      "eta" : 0,
      "elapsed" : 11,
      "job options" : {
        "rw" : "read",
        "name" : "read_B4096_Q1_T4",
        "bs" : "4096k",
        "iodepth" : "1",
        "numjobs" : "4",
        "runtime" : "10",
        "direct" : "1",
        "ioengine" : "libaio",
        "size" : "1G",
        "filename" : "/mnt/pve/test/write"
      },
      "read" : {
        "io_bytes" : 742391808,
        "io_kbytes" : 724992,
        "bw_bytes" : 74157607,
        "bw" : 72419,
        "iops" : 17.680551,
        "runtime" : 10011,
        "total_ios" : 177,
        "short_ios" : 0,
        "drop_ios" : 0,
        "slat_ns" : {
          "min" : 27413434,
          "max" : 76672061,
          "mean" : 47088984.242938,
          "stddev" : 7755327.720020,
          "N" : 177
        },
        "clat_ns" : {
          "min" : 801938,
          "max" : 53040861,
          "mean" : 9462464.983051,
          "stddev" : 7545312.001899,
          "N" : 177,
          "percentile" : {
            "1.000000" : 815104,
            "5.000000" : 1220608,
            "10.000000" : 2179072,
            "20.000000" : 3751936,
            "30.000000" : 5275648,
            "40.000000" : 6324224,
            "50.000000" : 7110656,
            "60.000000" : 9371648,
            "70.000000" : 11599872,
            "80.000000" : 14483456,
            "90.000000" : 18481152,
            "95.000000" : 21626880,
            "99.000000" : 33816576,
            "99.500000" : 53215232,
            "99.900000" : 53215232,
            "99.950000" : 53215232,
            "99.990000" : 53215232
          }
        },
        "lat_ns" : {
          "min" : 30072657,
          "max" : 108906896,
          "mean" : 56551449.225989,
          "stddev" : 10889154.149109,
          "N" : 177
        },
        "bw_min" : 49152,
        "bw_max" : 81920,
        "bw_agg" : 24.271313,
        "bw_mean" : 72089.600000,
        "bw_dev" : 8235.002920,
        "bw_samples" : 20,
        "iops_min" : 12,
        "iops_max" : 20,
        "iops_mean" : 17.600000,
        "iops_stddev" : 2.010499,
        "iops_samples" : 20
      },
      "write" : {
        "io_bytes" : 0,
        "io_kbytes" : 0,
        "bw_bytes" : 0,
        "bw" : 0,
        "iops" : 0.000000,
        "runtime" : 0,
        "total_ios" : 0,
        "short_ios" : 0,
        "drop_ios" : 0,
        "slat_ns" : {
          "min" : 0,
          "max" : 0,
          "mean" : 0.000000,
          "stddev" : 0.000000,
          "N" : 0
        },
        "clat_ns" : {
          "min" : 0,
          "max" : 0,
          "mean" : 0.000000,
          "stddev" : 0.000000,
          "N" : 0
        },
        "lat_ns" : {
          "min" : 0,
          "max" : 0,
          "mean" : 0.000000,
          "stddev" : 0.000000,
          "N" : 0
        },
        "bw_min" : 0,
        "bw_max" : 0,
        "bw_agg" : 0.000000,
        "bw_mean" : 0.000000,
        "bw_dev" : 0.000000,
        "bw_samples" : 0,
        "iops_min" : 0,
        "iops_max" : 0,
        "iops_mean" : 0.000000,
        "iops_stddev" : 0.000000,
        "iops_samples" : 0
      },
      "trim" : {
        "io_bytes" : 0,
        "io_kbytes" : 0,
        "bw_bytes" : 0,
        "bw" : 0,
        "iops" : 0.000000,
        "runtime" : 0,
        "total_ios" : 0,
        "short_ios" : 0,
        "drop_ios" : 0,
        "slat_ns" : {
          "min" : 0,
          "max" : 0,
          "mean" : 0.000000,
          "stddev" : 0.000000,
          "N" : 0
        },
        "clat_ns" : {
          "min" : 0,
          "max" : 0,
          "mean" : 0.000000,
          "stddev" : 0.000000,
          "N" : 0
        },
        "lat_ns" : {
          "min" : 0,
          "max" : 0,
          "mean" : 0.000000,
          "stddev" : 0.000000,
          "N" : 0
        },
        "bw_min" : 0,
        "bw_max" : 0,
        "bw_agg" : 0.000000,
        "bw_mean" : 0.000000,
        "bw_dev" : 0.000000,
        "bw_samples" : 0,
        "iops_min" : 0,
        "iops_max" : 0,
        "iops_mean" : 0.000000,
        "iops_stddev" : 0.000000,
        "iops_samples" : 0
      },
      "sync" : {
        "total_ios" : 0,
        "lat_ns" : {
          "min" : 0,
          "max" : 0,
          "mean" : 0.000000,
          "stddev" : 0.000000,
          "N" : 0
        }
      },
      "job_runtime" : 10010,
      "usr_cpu" : 0.039960,
      "sys_cpu" : 9.860140,
      "ctx" : 37979,
      "majf" : 0,
      "minf" : 1035,
      "iodepth_level" : {
        "1" : 100.000000,
        "2" : 0.000000,
        "4" : 0.000000,
        "8" : 0.000000,
        "16" : 0.000000,
        "32" : 0.000000,
        ">=64" : 0.000000
      },
      "iodepth_submit" : {
        "0" : 0.000000,
        "4" : 100.000000,
        "8" : 0.000000,
        "16" : 0.000000,
        "32" : 0.000000,
        "64" : 0.000000,
        ">=64" : 0.000000
      },
      "iodepth_complete" : {
        "0" : 0.000000,
        "4" : 100.000000,
        "8" : 0.000000,
        "16" : 0.000000,
        "32" : 0.000000,
        "64" : 0.000000,
        ">=64" : 0.000000
      },
      "latency_ns" : {
        "2" : 0.000000,
        "4" : 0.000000,
        "10" : 0.000000,
        "20" : 0.000000,
        "50" : 0.000000,
        "100" : 0.000000,
        "250" : 0.000000,
        "500" : 0.000000,
        "750" : 0.000000,
        "1000" : 0.000000
      },
      "latency_us" : {
        "2" : 0.000000,
        "4" : 0.000000,
        "10" : 0.000000,
        "20" : 0.000000,
        "50" : 0.000000,
        "100" : 0.000000,
        "250" : 0.000000,
        "500" : 0.000000,
        "750" : 0.000000,
        "1000" : 1.694915
      },
      "latency_ms" : {
        "2" : 7.909605,
        "4" : 11.864407,
        "10" : 41.807910,
        "20" : 29.943503,
        "50" : 6.214689,
        "100" : 0.564972,
        "250" : 0.000000,
        "500" : 0.000000,
        "750" : 0.000000,
        "1000" : 0.000000,
        "2000" : 0.000000,
        ">=2000" : 0.000000
      },
      "latency_depth" : 1,
      "latency_target" : 0,
      "latency_percentile" : 100.000000,
      "latency_window" : 0
    },
    {
      "jobname" : "test",
      "groupid" : 0,
      "error" : 0,
      "eta" : 0,
      "elapsed" : 11,
      "job options" : {
        "rw" : "read",
        "name" : "read_B4096_Q1_T4",
        "bs" : "4096k",
        "iodepth" : "1",
        "numjobs" : "4",
        "runtime" : "10",
        "direct" : "1",
        "ioengine" : "libaio",
        "size" : "1G",
        "filename" : "/mnt/pve/test/write"
      },
      "read" : {
        "io_bytes" : 767557632,
        "io_kbytes" : 749568,
        "bw_bytes" : 76725073,
        "bw" : 74926,
        "iops" : 18.292683,
        "runtime" : 10004,
        "total_ios" : 183,
        "short_ios" : 0,
        "drop_ios" : 0,
        "slat_ns" : {
          "min" : 21485885,
          "max" : 95185809,
          "mean" : 48072458.562842,
          "stddev" : 7871672.132546,
          "N" : 183
        },
        "clat_ns" : {
          "min" : 975356,
          "max" : 20955501,
          "mean" : 6585484.120219,
          "stddev" : 3524052.771495,
          "N" : 183,
          "percentile" : {
            "1.000000" : 1286144,
            "5.000000" : 1728512,
            "10.000000" : 2801664,
            "20.000000" : 3784704,
            "30.000000" : 4489216,
            "40.000000" : 5144576,
            "50.000000" : 6127616,
            "60.000000" : 6914048,
            "70.000000" : 7831552,
            "80.000000" : 8716288,
            "90.000000" : 11206656,
            "95.000000" : 13697024,
            "99.000000" : 19529728,
            "99.500000" : 20840448,
            "99.900000" : 20840448,
            "99.950000" : 20840448,
            "99.990000" : 20840448
          }
        },
        "lat_ns" : {
          "min" : 28386857,
          "max" : 109098263,
          "mean" : 54657942.683060,
          "stddev" : 9074485.407347,
          "N" : 183
        },
        "bw_min" : 49152,
        "bw_max" : 81920,
        "bw_agg" : 24.968252,
        "bw_mean" : 74159.157895,
        "bw_dev" : 8404.814660,
        "bw_samples" : 19,
        "iops_min" : 12,
        "iops_max" : 20,
        "iops_mean" : 18.105263,
        "iops_stddev" : 2.051957,
        "iops_samples" : 19
      },
      "write" : {
        "io_bytes" : 0,
        "io_kbytes" : 0,
        "bw_bytes" : 0,
        "bw" : 0,
        "iops" : 0.000000,
        "runtime" : 0,
        "total_ios" : 0,
        "short_ios" : 0,
        "drop_ios" : 0,
        "slat_ns" : {
          "min" : 0,
          "max" : 0,
          "mean" : 0.000000,
          "stddev" : 0.000000,
          "N" : 0
        },
        "clat_ns" : {
          "min" : 0,
          "max" : 0,
          "mean" : 0.000000,
          "stddev" : 0.000000,
          "N" : 0
        },
        "lat_ns" : {
          "min" : 0,
          "max" : 0,
          "mean" : 0.000000,
          "stddev" : 0.000000,
          "N" : 0
        },
        "bw_min" : 0,
        "bw_max" : 0,
        "bw_agg" : 0.000000,
        "bw_mean" : 0.000000,
        "bw_dev" : 0.000000,
        "bw_samples" : 0,
        "iops_min" : 0,
        "iops_max" : 0,
        "iops_mean" : 0.000000,
        "iops_stddev" : 0.000000,
        "iops_samples" : 0
      },
      "trim" : {
        "io_bytes" : 0,
        "io_kbytes" : 0,
        "bw_bytes" : 0,
        "bw" : 0,
        "iops" : 0.000000,
        "runtime" : 0,
        "total_ios" : 0,
        "short_ios" : 0,
        "drop_ios" : 0,
        "slat_ns" : {
          "min" : 0,
          "max" : 0,
          "mean" : 0.000000,
          "stddev" : 0.000000,
          "N" : 0
        },
        "clat_ns" : {
          "min" : 0,
          "max" : 0,
          "mean" : 0.000000,
          "stddev" : 0.000000,
          "N" : 0
        },
        "lat_ns" : {
          "min" : 0,
          "max" : 0,
          "mean" : 0.000000,
          "stddev" : 0.000000,
          "N" : 0
        },
        "bw_min" : 0,
        "bw_max" : 0,
        "bw_agg" : 0.000000,
        "bw_mean" : 0.000000,
        "bw_dev" : 0.000000,
        "bw_samples" : 0,
        "iops_min" : 0,
        "iops_max" : 0,
        "iops_mean" : 0.000000,
        "iops_stddev" : 0.000000,
        "iops_samples" : 0
      },
      "sync" : {
        "total_ios" : 0,
        "lat_ns" : {
          "min" : 0,
          "max" : 0,
          "mean" : 0.000000,
          "stddev" : 0.000000,
          "N" : 0
        }
      },
      "job_runtime" : 10003,
      "usr_cpu" : 0.029991,
      "sys_cpu" : 10.286914,
      "ctx" : 39948,
      "majf" : 0,
      "minf" : 1051,
      "iodepth_level" : {
        "1" : 100.000000,
        "2" : 0.000000,
        "4" : 0.000000,
        "8" : 0.000000,
        "16" : 0.000000,
        "32" : 0.000000,
        ">=64" : 0.000000
      },
      "iodepth_submit" : {
        "0" : 0.000000,
        "4" : 100.000000,
        "8" : 0.000000,
        "16" : 0.000000,
        "32" : 0.000000,
        "64" : 0.000000,
        ">=64" : 0.000000
      },
      "iodepth_complete" : {
        "0" : 0.000000,
        "4" : 100.000000,
        "8" : 0.000000,
        "16" : 0.000000,
        "32" : 0.000000,
        "64" : 0.000000,
        ">=64" : 0.000000
      },
      "latency_ns" : {
        "2" : 0.000000,
        "4" : 0.000000,
        "10" : 0.000000,
        "20" : 0.000000,
        "50" : 0.000000,
        "100" : 0.000000,
        "250" : 0.000000,
        "500" : 0.000000,
        "750" : 0.000000,
        "1000" : 0.000000
      },
      "latency_us" : {
        "2" : 0.000000,
        "4" : 0.000000,
        "10" : 0.000000,
        "20" : 0.000000,
        "50" : 0.000000,
        "100" : 0.000000,
        "250" : 0.000000,
        "500" : 0.000000,
        "750" : 0.000000,
        "1000" : 0.546448
      },
      "latency_ms" : {
        "2" : 4.918033,
        "4" : 18.032787,
        "10" : 62.295082,
        "20" : 13.661202,
        "50" : 0.546448,
        "100" : 0.000000,
        "250" : 0.000000,
        "500" : 0.000000,
        "750" : 0.000000,
        "1000" : 0.000000,
        "2000" : 0.000000,
        ">=2000" : 0.000000
      },
      "latency_depth" : 1,
      "latency_target" : 0,
      "latency_percentile" : 100.000000,
      "latency_window" : 0
    },
    {
      "jobname" : "test",
      "groupid" : 0,
      "error" : 0,
      "eta" : 0,
      "elapsed" : 11,
      "job options" : {
        "rw" : "read",
        "name" : "read_B4096_Q1_T4",
        "bs" : "4096k",
        "iodepth" : "1",
        "numjobs" : "4",
        "runtime" : "10",
        "direct" : "1",
        "ioengine" : "libaio",
        "size" : "1G",
        "filename" : "/mnt/pve/test/write"
      },
      "read" : {
        "io_bytes" : 767557632,
        "io_kbytes" : 749568,
        "bw_bytes" : 76663766,
        "bw" : 74866,
        "iops" : 18.278066,
        "runtime" : 10012,
        "total_ios" : 183,
        "short_ios" : 0,
        "drop_ios" : 0,
        "slat_ns" : {
          "min" : 29982082,
          "max" : 95150115,
          "mean" : 47250808.065574,
          "stddev" : 7764317.346997,
          "N" : 183
        },
        "clat_ns" : {
          "min" : 813057,
          "max" : 25363003,
          "mean" : 7448709.508197,
          "stddev" : 4722210.609423,
          "N" : 183,
          "percentile" : {
            "1.000000" : 987136,
            "5.000000" : 1400832,
            "10.000000" : 1728512,
            "20.000000" : 3194880,
            "30.000000" : 4145152,
            "40.000000" : 5537792,
            "50.000000" : 6520832,
            "60.000000" : 7831552,
            "70.000000" : 9371648,
            "80.000000" : 12124160,
            "90.000000" : 14090240,
            "95.000000" : 15269888,
            "99.000000" : 20840448,
            "99.500000" : 25296896,
            "99.900000" : 25296896,
            "99.950000" : 25296896,
            "99.990000" : 25296896
          }
        },
        "lat_ns" : {
          "min" : 31909770,
          "max" : 109133314,
          "mean" : 54699517.573771,
          "stddev" : 8674545.679757,
          "N" : 183
        },
        "bw_min" : 57344,
        "bw_max" : 81920,
        "bw_agg" : 25.098886,
        "bw_mean" : 74547.200000,
        "bw_dev" : 6455.860639,
        "bw_samples" : 20,
        "iops_min" : 14,
        "iops_max" : 20,
        "iops_mean" : 18.200000,
        "iops_stddev" : 1.576138,
        "iops_samples" : 20
      },
      "write" : {
        "io_bytes" : 0,
        "io_kbytes" : 0,
        "bw_bytes" : 0,
        "bw" : 0,
        "iops" : 0.000000,
        "runtime" : 0,
        "total_ios" : 0,
        "short_ios" : 0,
        "drop_ios" : 0,
        "slat_ns" : {
          "min" : 0,
          "max" : 0,
          "mean" : 0.000000,
          "stddev" : 0.000000,
          "N" : 0
        },
        "clat_ns" : {
          "min" : 0,
          "max" : 0,
          "mean" : 0.000000,
          "stddev" : 0.000000,
          "N" : 0
        },
        "lat_ns" : {
          "min" : 0,
          "max" : 0,
          "mean" : 0.000000,
          "stddev" : 0.000000,
          "N" : 0
        },
        "bw_min" : 0,
        "bw_max" : 0,
        "bw_agg" : 0.000000,
        "bw_mean" : 0.000000,
        "bw_dev" : 0.000000,
        "bw_samples" : 0,
        "iops_min" : 0,
        "iops_max" : 0,
        "iops_mean" : 0.000000,
        "iops_stddev" : 0.000000,
        "iops_samples" : 0
      },
      "trim" : {
        "io_bytes" : 0,
        "io_kbytes" : 0,
        "bw_bytes" : 0,
        "bw" : 0,
        "iops" : 0.000000,
        "runtime" : 0,
        "total_ios" : 0,
        "short_ios" : 0,
        "drop_ios" : 0,
        "slat_ns" : {
          "min" : 0,
          "max" : 0,
          "mean" : 0.000000,
          "stddev" : 0.000000,
          "N" : 0
        },
        "clat_ns" : {
          "min" : 0,
          "max" : 0,
          "mean" : 0.000000,
          "stddev" : 0.000000,
          "N" : 0
        },
        "lat_ns" : {
          "min" : 0,
          "max" : 0,
          "mean" : 0.000000,
          "stddev" : 0.000000,
          "N" : 0
        },
        "bw_min" : 0,
        "bw_max" : 0,
        "bw_agg" : 0.000000,
        "bw_mean" : 0.000000,
        "bw_dev" : 0.000000,
        "bw_samples" : 0,
        "iops_min" : 0,
        "iops_max" : 0,
        "iops_mean" : 0.000000,
        "iops_stddev" : 0.000000,
        "iops_samples" : 0
      },
      "sync" : {
        "total_ios" : 0,
        "lat_ns" : {
          "min" : 0,
          "max" : 0,
          "mean" : 0.000000,
          "stddev" : 0.000000,
          "N" : 0
        }
      },
      "job_runtime" : 10011,
      "usr_cpu" : 0.059934,
      "sys_cpu" : 10.228748,
      "ctx" : 39243,
      "majf" : 0,
      "minf" : 2684,
      "iodepth_level" : {
        "1" : 100.000000,
        "2" : 0.000000,
        "4" : 0.000000,
        "8" : 0.000000,
        "16" : 0.000000,
        "32" : 0.000000,
        ">=64" : 0.000000
      },
      "iodepth_submit" : {
        "0" : 0.000000,
        "4" : 100.000000,
        "8" : 0.000000,
        "16" : 0.000000,
        "32" : 0.000000,
        "64" : 0.000000,
        ">=64" : 0.000000
      },
      "iodepth_complete" : {
        "0" : 0.000000,
        "4" : 100.000000,
        "8" : 0.000000,
        "16" : 0.000000,
        "32" : 0.000000,
        "64" : 0.000000,
        ">=64" : 0.000000
      },
      "latency_ns" : {
        "2" : 0.000000,
        "4" : 0.000000,
        "10" : 0.000000,
        "20" : 0.000000,
        "50" : 0.000000,
        "100" : 0.000000,
        "250" : 0.000000,
        "500" : 0.000000,
        "750" : 0.000000,
        "1000" : 0.000000
      },
      "latency_us" : {
        "2" : 0.000000,
        "4" : 0.000000,
        "10" : 0.000000,
        "20" : 0.000000,
        "50" : 0.000000,
        "100" : 0.000000,
        "250" : 0.000000,
        "500" : 0.000000,
        "750" : 0.000000,
        "1000" : 2.185792
      },
      "latency_ms" : {
        "2" : 8.743169,
        "4" : 15.846995,
        "10" : 47.540984,
        "20" : 24.590164,
        "50" : 1.092896,
        "100" : 0.000000,
        "250" : 0.000000,
        "500" : 0.000000,
        "750" : 0.000000,
        "1000" : 0.000000,
        "2000" : 0.000000,
        ">=2000" : 0.000000
      },
      "latency_depth" : 1,
      "latency_target" : 0,
      "latency_percentile" : 100.000000,
      "latency_window" : 0
    }
  ],
  "disk_util" : [
    {
      "name" : "sdb",
      "read_ios" : 367038,
      "write_ios" : 515,
      "read_merges" : 0,
      "write_merges" : 1,
      "read_ticks" : 2486564,
      "write_ticks" : 678,
      "in_queue" : 2487242,
      "util" : 99.019019
    }
  ]
}
